{"query":"013027","verses":[{},{"canonical":"1 Chronicles 27:1","passages":["ובני ישראל למספרם ראשי האבות ושרי האלפים והמאות ושטריהם המשרתים את המלך לכל דבר המחלקות הבאה והיצאת חדש בחדש לכל חדשי השנה המחלקת האחת עשרים וארבעה אלף  ס "],"query":"013027001"},{"canonical":"1 Chronicles 27:2","passages":["על המחלקת הראשונה לחדש הראשון ישבעם בן זבדיאל ועל מחלקתו עשרים וארבעה אלף "],"query":"013027002"},{"canonical":"1 Chronicles 27:3","passages":["מן בני פרץ הראש לכל שרי הצבאות לחדש הראשון "],"query":"013027003"},{"canonical":"1 Chronicles 27:4","passages":["ועל מחלקת החדש השני דודי האחוחי ומחלקתו ומקלות הנגיד ועל מחלקתו עשרים וארבעה אלף  ס "],"query":"013027004"},{"canonical":"1 Chronicles 27:5","passages":["שר הצבא השלישי לחדש השלישי בניהו בן יהוידע הכהן ראש ועל מחלקתו עשרים וארבעה אלף "],"query":"013027005"},{"canonical":"1 Chronicles 27:6","passages":["הוא בניהו גבור השלשים ועל השלשים ומחלקתו עמיזבד בנו  ס "],"query":"013027006"},{"canonical":"1 Chronicles 27:7","passages":["הרביעי לחדש הרביעי עשה אל אחי יואב וזבדיה בנו אחריו ועל מחלקתו עשרים וארבעה אלף  ס "],"query":"013027007"},{"canonical":"1 Chronicles 27:8","passages":["החמישי לחדש החמישי השר שמהות היזרח ועל מחלקתו עשרים וארבעה אלף  ס "],"query":"013027008"},{"canonical":"1 Chronicles 27:9","passages":["הששי לחדש הששי עירא בן עקש התקועי ועל מחלקתו עשרים וארבעה אלף  ס "],"query":"013027009"},{"canonical":"1 Chronicles 27:10","passages":["השביעי לחדש השביעי חלץ הפלוני מן בני אפרים ועל מחלקתו עשרים וארבעה אלף  ס "],"query":"013027010"},{"canonical":"1 Chronicles 27:11","passages":["השמיני לחדש השמיני סבכי החשתי לזרחי ועל מחלקתו עשרים וארבעה אלף  ס "],"query":"013027011"},{"canonical":"1 Chronicles 27:12","passages":["התשיעי לחדש התשיעי אביעזר הענתתי  ס "],"query":"013027012"},{"canonical":"1 Chronicles 27:13","passages":["העשירי לחדש העשירי מהרי הנטופתי לזרחי ועל מחלקתו עשרים וארבעה אלף  ס "],"query":"013027013"},{"canonical":"1 Chronicles 27:14","passages":["עשתי עשר לעשתי עשר החדש בניה הפרעתוני מן בני אפרים ועל מחלקתו עשרים וארבעה אלף  ס "],"query":"013027014"},{"canonical":"1 Chronicles 27:15","passages":["השנים עשר לשנים עשר החדש חלדי הנטופתי לעתניאל ועל מחלקתו עשרים וארבעה אלף פ"],"query":"013027015"},{"canonical":"1 Chronicles 27:16","passages":["ועל שבטי ישראל לראובני נגיד אליעזר בן זכרי  ס "],"query":"013027016"},{"canonical":"1 Chronicles 27:17","passages":["ללוי חשביה בן קמואל לאהרן צדוק  ס "],"query":"013027017"},{"canonical":"1 Chronicles 27:18","passages":["ליהודה אליהו מאחי דויד ליששכר עמרי בן מיכאל  ס "],"query":"013027018"},{"canonical":"1 Chronicles 27:19","passages":["לזבולן ישמעיהו בן עבדיהו לנפתלי ירימות בן עזריאל  ס "],"query":"013027019"},{"canonical":"1 Chronicles 27:20","passages":["לבני אפרים הושע בן עזזיהו לחצי שבט מנשה יואל בן פדיהו  ס "],"query":"013027020"},{"canonical":"1 Chronicles 27:21","passages":["לחצי המנשה גלעדה ידו בן זכריהו  ס "],"query":"013027021"},{"canonical":"1 Chronicles 27:22","passages":["לדן עזראל בן ירחם אלה שרי שבטי ישראל "],"query":"013027022"},{"canonical":"1 Chronicles 27:23","passages":["ולא נשא דויד מספרם למבן עשרים שנה ולמטה כי אמר יהוה להרבות את ישראל ככוכבי השמים "],"query":"013027023"},{"canonical":"1 Chronicles 27:24","passages":["יואב בן צרויה החל למנות ולא כלה ויהי בזאת קצף על ישראל ולא עלה המספר במספר דברי הימים למלך דויד  ס "],"query":"013027024"},{"canonical":"1 Chronicles 27:25","passages":["ועל אצרות המלך עזמות בן עדיאל  ס "],"query":"013027025"},{"canonical":"1 Chronicles 27:26","passages":["ועל עשי מלאכת השדה לעבדת האדמה עזרי בן כלוב "],"query":"013027026"},{"canonical":"1 Chronicles 27:27","passages":["ועל הכרמים שמעי הרמתי ועל שבכרמים לאצרות היין זבדי השפמי  ס "],"query":"013027027"},{"canonical":"1 Chronicles 27:28","passages":["ועל הזיתים והשקמים אשר בשפלה בעל חנן הגדרי  ס "],"query":"013027028"},{"canonical":"1 Chronicles 27:29","passages":["ועל הבקר הרעים בשרון  ס "],"query":"013027029"},{"canonical":"1 Chronicles 27:30","passages":["ועל הגמלים אוביל הישמעלי ועל האתנות יחדיהו המרנתי  ס "],"query":"013027030"},{"canonical":"1 Chronicles 27:31","passages":["ועל הצאן יזיז ההגרי כל אלה שרי הרכוש אשר למלך דויד "],"query":"013027031"},{"canonical":"1 Chronicles 27:32","passages":["ויהונתן דוד דויד יועץ איש מבין וסופר הוא ויחיאל בן חכמוני עם בני המלך "],"query":"013027032"},{"canonical":"1 Chronicles 27:33","passages":["ואחיתפל יועץ למלך  ס וחושי הארכי רע המלך "],"query":"013027033"},{"canonical":"1 Chronicles 27:34","passages":["ואחרי אחיתפל יהוידע בן בניהו ואביתר ושר צבא למלך יואב פ"],"query":"013027034"}]}