{"query":"018013","verses":[{},{"canonical":"Job 13:1","passages":["הן כל ראתה עיני שמעה אזני ותבן לה "],"query":"018013001"},{"canonical":"Job 13:2","passages":["כדעתכם ידעתי גם אני לא נפל אנכי מכם "],"query":"018013002"},{"canonical":"Job 13:3","passages":["אולם אני אל שדי אדבר והוכח אל אל אחפץ "],"query":"018013003"},{"canonical":"Job 13:4","passages":["ואולם אתם טפלי שקר רפאי אלל כלכם "],"query":"018013004"},{"canonical":"Job 13:5","passages":["מי יתן החרש תחרישון ותהי לכם לחכמה "],"query":"018013005"},{"canonical":"Job 13:6","passages":["שמעו נא תוכחתי ורבות שפתי הקשיבו "],"query":"018013006"},{"canonical":"Job 13:7","passages":["הלאל תדברו עולה ולו תדברו רמיה "],"query":"018013007"},{"canonical":"Job 13:8","passages":["הפניו תשאון אם לאל תריבון "],"query":"018013008"},{"canonical":"Job 13:9","passages":["הטוב כי יחקר אתכם אם כהתל באנוש תהתלו בו "],"query":"018013009"},{"canonical":"Job 13:10","passages":["הוכח יוכיח אתכם אם בסתר פנים תשאון "],"query":"018013010"},{"canonical":"Job 13:11","passages":["הלא שאתו תבעת אתכם ופחדו יפל עליכם "],"query":"018013011"},{"canonical":"Job 13:12","passages":["זכרניכם משלי אפר לגבי חמר גביכם "],"query":"018013012"},{"canonical":"Job 13:13","passages":["החרישו ממני ואדברה אני ויעבר עלי מה "],"query":"018013013"},{"canonical":"Job 13:14","passages":["על מה אשא בשרי בשני ונפשי אשים בכפי "],"query":"018013014"},{"canonical":"Job 13:15","passages":["הן יקטלני לו איחל אך דרכי אל פניו אוכיח "],"query":"018013015"},{"canonical":"Job 13:16","passages":["גם הוא לי לישועה כי לא לפניו חנף יבוא "],"query":"018013016"},{"canonical":"Job 13:17","passages":["שמעו שמוע מלתי וא͏חותי באזניכם "],"query":"018013017"},{"canonical":"Job 13:18","passages":["הנה נא ערכתי משפט ידעתי כי אני אצדק "],"query":"018013018"},{"canonical":"Job 13:19","passages":["מי הוא יריב עמדי כי עתה אחריש ואגוע "],"query":"018013019"},{"canonical":"Job 13:20","passages":["אך שתים אל תעש עמדי אז מפניך לא אסתר "],"query":"018013020"},{"canonical":"Job 13:21","passages":["כפך מעלי הרחק ואמתך אל תבעתני "],"query":"018013021"},{"canonical":"Job 13:22","passages":["וקרא ואנכי אענה או אדבר והשיבני "],"query":"018013022"},{"canonical":"Job 13:23","passages":["כמה לי עונות וחטאות פשעי וחטאתי הדיעני "],"query":"018013023"},{"canonical":"Job 13:24","passages":["למה פניך תסתיר ותחשבני לאויב לך "],"query":"018013024"},{"canonical":"Job 13:25","passages":["העלה נדף תערוץ ואת קש יבש תרדף "],"query":"018013025"},{"canonical":"Job 13:26","passages":["כי תכתב עלי מררות ותורישני עונות נעורי "],"query":"018013026"},{"canonical":"Job 13:27","passages":["ותשם בסד רגלי ותשמור כל ארחותי על שרשי רגלי תתחקה "],"query":"018013027"},{"canonical":"Job 13:28","passages":["והוא כרקב יבלה כבגד אכלו עש "],"query":"018013028"}]}