{"query":"019049","verses":[{},{"canonical":"Psalm 49:1","passages":["למנצח לבני קרח מזמור "],"query":"019049001"},{"canonical":"Psalm 49:2","passages":["שמעו זאת כל העמים האזינו כל ישבי חלד "],"query":"019049002"},{"canonical":"Psalm 49:3","passages":["גם בני אדם גם בני איש יחד עשיר ואביון "],"query":"019049003"},{"canonical":"Psalm 49:4","passages":["פי ידבר חכמות והגות לבי תבונות "],"query":"019049004"},{"canonical":"Psalm 49:5","passages":["אטה למשל אזני אפתח בכנור חידת͏י "],"query":"019049005"},{"canonical":"Psalm 49:6","passages":["למה אירא בימי רע עון עקבי יסובני "],"query":"019049006"},{"canonical":"Psalm 49:7","passages":["הבטחים על חילם וברב עשרם יתהללו "],"query":"019049007"},{"canonical":"Psalm 49:8","passages":["אח לא פדה יפדה איש לא יתן לאלהים כפרו "],"query":"019049008"},{"canonical":"Psalm 49:9","passages":["ויקר פדיון נפשם וחדל לעולם "],"query":"019049009"},{"canonical":"Psalm 49:10","passages":["ויחי עוד לנצח לא יראה השחת "],"query":"019049010"},{"canonical":"Psalm 49:11","passages":["כי יראה חכמים ימותו יחד כסיל ובער יאבדו ועזבו לאחרים חילם "],"query":"019049011"},{"canonical":"Psalm 49:12","passages":["קרבם בתימו לעולם משכנתם לדר ודר קראו בשמותם עלי אדמות "],"query":"019049012"},{"canonical":"Psalm 49:13","passages":["ואדם ביקר בל ילין נמשל כבהמות נדמו "],"query":"019049013"},{"canonical":"Psalm 49:14","passages":["זה דרכם כסל למו ואחריהם בפיהם ירצו סלה "],"query":"019049014"},{"canonical":"Psalm 49:15","passages":["כצאן לשאול שתו מות ירעם וירדו בם ישרים לבקר וצורם לבלות שאול מזבל לו "],"query":"019049015"},{"canonical":"Psalm 49:16","passages":["אך אלהים יפדה נפשי מיד שאול כי יקחני סלה "],"query":"019049016"},{"canonical":"Psalm 49:17","passages":["אל תירא כי יעשר איש כי ירבה כבוד ביתו "],"query":"019049017"},{"canonical":"Psalm 49:18","passages":["כי לא במותו יקח הכל לא ירד אחריו כבודו "],"query":"019049018"},{"canonical":"Psalm 49:19","passages":["כי נפשו בחייו יברך ויודך כי תיטיב לך "],"query":"019049019"},{"canonical":"Psalm 49:20","passages":["תבוא עד דור אבותיו עד נצח לא יראו אור "],"query":"019049020"},{"canonical":"Psalm 49:21","passages":["אדם ביקר ולא יבין נמשל כבהמות נדמו "],"query":"019049021"}]}